odoo/addons/ssi_odoo_implementation_project/README.rst
odoo/addons/ssi_odoo_implementation_project/__init__.py
odoo/addons/ssi_odoo_implementation_project/__manifest__.py
odoo/addons/ssi_odoo_implementation_project/models/__init__.py
odoo/addons/ssi_odoo_implementation_project/models/odoo_deployment.py
odoo/addons/ssi_odoo_implementation_project/models/odoo_feature.py
odoo/addons/ssi_odoo_implementation_project/models/odoo_feature_implementation.py
odoo/addons/ssi_odoo_implementation_project/models/odoo_implementation.py
odoo/addons/ssi_odoo_implementation_project/models/odoo_implementation_update.py
odoo/addons/ssi_odoo_implementation_project/models/project_task.py
odoo/addons/ssi_odoo_implementation_project/static/description/icon.png
odoo/addons/ssi_odoo_implementation_project/views/odoo_deployment_views.xml
odoo/addons/ssi_odoo_implementation_project/views/odoo_feature_implementation_views.xml
odoo/addons/ssi_odoo_implementation_project/views/odoo_feature_views.xml
odoo/addons/ssi_odoo_implementation_project/views/odoo_implementation_views.xml
odoo14_addon_ssi_odoo_implementation_project-14.0.1.6.0.dist-info/METADATA
odoo14_addon_ssi_odoo_implementation_project-14.0.1.6.0.dist-info/WHEEL
odoo14_addon_ssi_odoo_implementation_project-14.0.1.6.0.dist-info/top_level.txt
odoo14_addon_ssi_odoo_implementation_project-14.0.1.6.0.dist-info/RECORD
